<Properties StartupConfiguration="{0985F0B3-47B0-4667-9BDA-EC005B2B46CB}|Default">
  <MonoDevelop.Ide.Workbench ActiveDocument="KemblaJoggers/View Controllers/filterParticipationViewController.cs">
    <Files>
      <File FileName="KemblaJoggers/View Controllers/filterParticipationViewController.cs" Line="17" Column="9" />
      <File FileName="KemblaJoggers/View Controllers/viewRaceRecordViewController.cs" Line="20" Column="45" />
      <File FileName="KemblaJoggers/Classes/ParticipationDataSource.cs" Line="23" Column="42" />
      <File FileName="KemblaJoggers/Classes/HandicapDataSource.cs" Line="33" Column="10" />
      <File FileName="KemblaJoggers/ParticipationViewController.cs" Line="18" Column="12" />
      <File FileName="KemblaJoggers/Classes/ParticipationCell.cs" Line="14" Column="10" />
      <File FileName="KemblaJoggers/Main.cs" Line="12" Column="59" />
      <File FileName="KemblaJoggers/LaunchScreen.storyboard" />
    </Files>
  </MonoDevelop.Ide.Workbench>
  <MonoDevelop.Ide.Workspace ActiveConfiguration="Debug|iPhoneSimulator" />
  <MonoDevelop.Ide.DebuggingService.Breakpoints>
    <BreakpointStore />
  </MonoDevelop.Ide.DebuggingService.Breakpoints>
  <MonoDevelop.Ide.DebuggingService.PinnedWatches />
  <MonoDevelop.Ide.ItemProperties.KemblaJoggers PreferredExecutionTarget="MonoDevelop.IPhone.IPhoneSimulatorTarget.3140C334-BC86-4DB3-9290-82D67A2BCF55" />
  <MultiItemStartupConfigurations />
</Properties>